ocm_python_wrapper/__init__.py
ocm_python_wrapper/cluster.py
ocm_python_wrapper/exceptions.py
ocm_python_wrapper/manifests/managed-api-service-policy.json
ocm_python_wrapper/ocm_client.py
openshift_cluster_management_python_wrapper-1.0.33.dist-info/LICENSE
openshift_cluster_management_python_wrapper-1.0.33.dist-info/METADATA
openshift_cluster_management_python_wrapper-1.0.33.dist-info/WHEEL
openshift_cluster_management_python_wrapper-1.0.33.dist-info/RECORD
