Metadata-Version: 2.1
Name: openshift-cluster-management-python-wrapper
Version: 1.0.33
Summary: Wrapper around https://github.com/openshift/openshift-cluster-management-python-client
Home-page: https://github.com/RedHatQE/openshift-cluster-management-python-wrapper
License: Apache-2.0
Keywords: Openshift,OCM
Author: Meni Yakove
Author-email: myakove@gmail.com
Requires-Python: >=3.8,<4.0
Classifier: License :: OSI Approved :: Apache Software License
Classifier: Operating System :: OS Independent
Classifier: Programming Language :: Python :: 3
Classifier: Programming Language :: Python :: 3.8
Classifier: Programming Language :: Python :: 3.9
Classifier: Programming Language :: Python :: 3.10
Classifier: Programming Language :: Python :: 3.11
Requires-Dist: colorlog (>=6.7.0,<7.0.0)
Requires-Dist: importlib (>=1.0.4,<2.0.0)
Requires-Dist: openshift-cluster-management-python-client (>=1.0.23,<2.0.0)
Requires-Dist: openshift-python-utilities (>=4.14.2,<5.0.0)
Requires-Dist: openshift-python-wrapper (>=4.14.4,<5.0.0)
Requires-Dist: python-benedict (>=0.32.0,<0.33.0)
Requires-Dist: python-simple-logger (>=1.0.5,<2.0.0)
Requires-Dist: pyyaml (>=6.0.1,<7.0.0)
Requires-Dist: redhat-qe-cloud-tools (>=1.0.10,<2.0.0)
Requires-Dist: requests (>=2.31.0,<3.0.0)
Requires-Dist: rosa-python-client (>=1.0.28,<2.0.0)
Project-URL: Bug Tracker, https://github.com/RedHatQE/openshift-cluster-management-python-wrapper/issues
Project-URL: Documentation, https://github.com/RedHatQE/openshift-cluster-management-python-wrapper/blob/main/README.md
Project-URL: Download, https://pypi.org/project/openshift-cluster-management-python-wrapper/
